{"id": "https:\/\/api.ap.org\/v2\/reports", "title": "Election Reports", "updated": "2020-11-02T21:09:55.430Z",  "reports": [{"id": "https:\/\/api.ap.org\/v2\/reports\/84a6938de664456ebdc4236660594eed", "title": "EstimatedVotePercentage \/ test \/ IL", "updated": "2020-11-02T16:10:01Z", "electionDate": "2020-11-03",  "categories": [{"term": "EstimatedVotePercentage", "scheme": "https:\/\/api.ap.org\/cv\/type\/"}, {"term": "true", "scheme": "https:\/\/api.ap.org\/cv\/test\/"}, {"term": "test", "scheme": "https:\/\/api.ap.org\/cv\/resultsType\/"}, {"term": "IL", "scheme": "https:\/\/api.ap.org\/cv\/geo\/"}], "contentLink": "https:\/\/api.ap.org\/v2\/reports\/84a6938de664456ebdc4236660594eed"}, {"id": "https:\/\/api.ap.org\/v2\/reports\/b8fe860d035a4d6994e481c332126691", "title": "EstimatedVotePercentage \/ test \/ CO", "updated": "2020-11-02T16:09:59Z", "electionDate": "2020-11-03",  "categories": [{"term": "EstimatedVotePercentage", "scheme": "https:\/\/api.ap.org\/cv\/type\/"}, {"term": "true", "scheme": "https:\/\/api.ap.org\/cv\/test\/"}, {"term": "test", "scheme": "https:\/\/api.ap.org\/cv\/resultsType\/"}, {"term": "CO", "scheme": "https:\/\/api.ap.org\/cv\/geo\/"}], "contentLink": "https:\/\/api.ap.org\/v2\/reports\/b8fe860d035a4d6994e481c332126691"}, {"id": "https:\/\/api.ap.org\/v2\/reports\/64a8dbb9594e413789f85e01472767b6", "title": "EstimatedVotePercentage \/ test \/ ID", "updated": "2020-11-02T16:09:59Z", "electionDate": "2020-11-03",  "categories": [{"term": "EstimatedVotePercentage", "scheme": "https:\/\/api.ap.org\/cv\/type\/"}, {"term": "true", "scheme": "https:\/\/api.ap.org\/cv\/test\/"}, {"term": "test", "scheme": "https:\/\/api.ap.org\/cv\/resultsType\/"}, {"term": "ID", "scheme": "https:\/\/api.ap.org\/cv\/geo\/"}], "contentLink": "https:\/\/api.ap.org\/v2\/reports\/64a8dbb9594e413789f85e01472767b6"}, {"id": "https:\/\/api.ap.org\/v2\/reports\/85d3acce408a4042b70af42f98e65cab", "title": "EstimatedVotePercentage \/ test \/ HI", "updated": "2020-11-02T16:09:58Z", "electionDate": "2020-11-03",  "categories": [{"term": "EstimatedVotePercentage", "scheme": "https:\/\/api.ap.org\/cv\/type\/"}, {"term": "true", "scheme": "https:\/\/api.ap.org\/cv\/test\/"}, {"term": "test", "scheme": "https:\/\/api.ap.org\/cv\/resultsType\/"}, {"term": "HI", "scheme": "https:\/\/api.ap.org\/cv\/geo\/"}], "contentLink": "https:\/\/api.ap.org\/v2\/reports\/85d3acce408a4042b70af42f98e65cab"}, {"id": "https:\/\/api.ap.org\/v2\/reports\/fe0afa51125f42f784901a3dbbdc2b28", "title": "EstimatedVotePercentage \/ test \/ DE", "updated": "2020-11-02T16:09:58Z", "electionDate": "2020-11-03",  "categories": [{"term": "EstimatedVotePercentage", "scheme": "https:\/\/api.ap.org\/cv\/type\/"}, {"term": "true", "scheme": "https:\/\/api.ap.org\/cv\/test\/"}, {"term": "test", "scheme": "https:\/\/api.ap.org\/cv\/resultsType\/"}, {"term": "DE", "scheme": "https:\/\/api.ap.org\/cv\/geo\/"}], "contentLink": "https:\/\/api.ap.org\/v2\/reports\/fe0afa51125f42f784901a3dbbdc2b28"}, {"id": "https:\/\/api.ap.org\/v2\/reports\/47c1134cf46c40939b51d35188d21ffa", "title": "EstimatedVotePercentage \/ test \/ FL", "updated": "2020-11-02T16:09:58Z", "electionDate": "2020-11-03",  "categories": [{"term": "EstimatedVotePercentage", "scheme": "https:\/\/api.ap.org\/cv\/type\/"}, {"term": "true", "scheme": "https:\/\/api.ap.org\/cv\/test\/"}, {"term": "test", "scheme": "https:\/\/api.ap.org\/cv\/resultsType\/"}, {"term": "FL", "scheme": "https:\/\/api.ap.org\/cv\/geo\/"}], "contentLink": "https:\/\/api.ap.org\/v2\/reports\/47c1134cf46c40939b51d35188d21ffa"}, {"id": "https:\/\/api.ap.org\/v2\/reports\/06db16db582546299f1bff90290a7ee1", "title": "EstimatedVotePercentage \/ test \/ CT", "updated": "2020-11-02T16:09:56Z", "electionDate": "2020-11-03",  "categories": [{"term": "EstimatedVotePercentage", "scheme": "https:\/\/api.ap.org\/cv\/type\/"}, {"term": "true", "scheme": "https:\/\/api.ap.org\/cv\/test\/"}, {"term": "test", "scheme": "https:\/\/api.ap.org\/cv\/resultsType\/"}, {"term": "CT", "scheme": "https:\/\/api.ap.org\/cv\/geo\/"}], "contentLink": "https:\/\/api.ap.org\/v2\/reports\/06db16db582546299f1bff90290a7ee1"}, {"id": "https:\/\/api.ap.org\/v2\/reports\/d14cc4b6193b4de399bb42977ecd61ae", "title": "EstimatedVotePercentage \/ test \/ DC", "updated": "2020-11-02T16:09:56Z", "electionDate": "2020-11-03",  "categories": [{"term": "EstimatedVotePercentage", "scheme": "https:\/\/api.ap.org\/cv\/type\/"}, {"term": "true", "scheme": "https:\/\/api.ap.org\/cv\/test\/"}, {"term": "test", "scheme": "https:\/\/api.ap.org\/cv\/resultsType\/"}, {"term": "DC", "scheme": "https:\/\/api.ap.org\/cv\/geo\/"}], "contentLink": "https:\/\/api.ap.org\/v2\/reports\/d14cc4b6193b4de399bb42977ecd61ae"}, {"id": "https:\/\/api.ap.org\/v2\/reports\/a09ef45555f5487e8934b61f80ce5fc7", "title": "EstimatedVotePercentage \/ test \/ AZ", "updated": "2020-11-02T16:09:56Z", "electionDate": "2020-11-03",  "categories": [{"term": "EstimatedVotePercentage", "scheme": "https:\/\/api.ap.org\/cv\/type\/"}, {"term": "true", "scheme": "https:\/\/api.ap.org\/cv\/test\/"}, {"term": "test", "scheme": "https:\/\/api.ap.org\/cv\/resultsType\/"}, {"term": "AZ", "scheme": "https:\/\/api.ap.org\/cv\/geo\/"}], "contentLink": "https:\/\/api.ap.org\/v2\/reports\/a09ef45555f5487e8934b61f80ce5fc7"}, {"id": "https:\/\/api.ap.org\/v2\/reports\/ccec42c0df86446b883afba58a83b73d", "title": "Pres \/ pres_summary \/ test \/ US", "updated": "2020-11-02T16:09:56Z", "electionDate": "2020-11-03",  "categories": [{"term": "Pres", "scheme": "https:\/\/api.ap.org\/cv\/type\/"}, {"term": "pres_summary", "scheme": "https:\/\/api.ap.org\/cv\/subtype\/"}, {"term": "true", "scheme": "https:\/\/api.ap.org\/cv\/test\/"}, {"term": "test", "scheme": "https:\/\/api.ap.org\/cv\/resultsType\/"}, {"term": "US", "scheme": "https:\/\/api.ap.org\/cv\/geo\/"}], "contentLink": "https:\/\/api.ap.org\/v2\/reports\/ccec42c0df86446b883afba58a83b73d"}, {"id": "https:\/\/api.ap.org\/v2\/reports\/237f7f5c77d04ef8aa706aa7ddc08e70", "title": "Pres \/ pres_summary_all \/ test \/ US", "updated": "2020-11-02T16:09:56Z", "electionDate": "2020-11-03",  "categories": [{"term": "Pres", "scheme": "https:\/\/api.ap.org\/cv\/type\/"}, {"term": "pres_summary_all", "scheme": "https:\/\/api.ap.org\/cv\/subtype\/"}, {"term": "true", "scheme": "https:\/\/api.ap.org\/cv\/test\/"}, {"term": "test", "scheme": "https:\/\/api.ap.org\/cv\/resultsType\/"}, {"term": "US", "scheme": "https:\/\/api.ap.org\/cv\/geo\/"}], "contentLink": "https:\/\/api.ap.org\/v2\/reports\/237f7f5c77d04ef8aa706aa7ddc08e70"}, {"id": "https:\/\/api.ap.org\/v2\/reports\/60da66268afc4d2b9b82a96dd39b71d6", "title": "Pres \/ statebystate_pres \/ test \/ US", "updated": "2020-11-02T16:09:56Z", "electionDate": "2020-11-03",  "categories": [{"term": "Pres", "scheme": "https:\/\/api.ap.org\/cv\/type\/"}, {"term": "statebystate_pres", "scheme": "https:\/\/api.ap.org\/cv\/subtype\/"}, {"term": "true", "scheme": "https:\/\/api.ap.org\/cv\/test\/"}, {"term": "test", "scheme": "https:\/\/api.ap.org\/cv\/resultsType\/"}, {"term": "US", "scheme": "https:\/\/api.ap.org\/cv\/geo\/"}], "contentLink": "https:\/\/api.ap.org\/v2\/reports\/60da66268afc4d2b9b82a96dd39b71d6"}, {"id": "https:\/\/api.ap.org\/v2\/reports\/7565b78798144a68bf8a85fb78f4fd85", "title": "EstimatedVotePercentage \/ test \/ CA", "updated": "2020-11-02T16:09:54Z", "electionDate": "2020-11-03",  "categories": [{"term": "EstimatedVotePercentage", "scheme": "https:\/\/api.ap.org\/cv\/type\/"}, {"term": "true", "scheme": "https:\/\/api.ap.org\/cv\/test\/"}, {"term": "test", "scheme": "https:\/\/api.ap.org\/cv\/resultsType\/"}, {"term": "CA", "scheme": "https:\/\/api.ap.org\/cv\/geo\/"}], "contentLink": "https:\/\/api.ap.org\/v2\/reports\/7565b78798144a68bf8a85fb78f4fd85"}, {"id": "https:\/\/api.ap.org\/v2\/reports\/03caa90872be4803b36bf9819c968dd5", "title": "EstimatedVotePercentage \/ test \/ AR", "updated": "2020-11-02T16:09:54Z", "electionDate": "2020-11-03",  "categories": [{"term": "EstimatedVotePercentage", "scheme": "https:\/\/api.ap.org\/cv\/type\/"}, {"term": "true", "scheme": "https:\/\/api.ap.org\/cv\/test\/"}, {"term": "test", "scheme": "https:\/\/api.ap.org\/cv\/resultsType\/"}, {"term": "AR", "scheme": "https:\/\/api.ap.org\/cv\/geo\/"}], "contentLink": "https:\/\/api.ap.org\/v2\/reports\/03caa90872be4803b36bf9819c968dd5"}, {"id": "https:\/\/api.ap.org\/v2\/reports\/6d17b969892742928e5cf5759a12e9fd", "title": "EstimatedVotePercentage \/ test \/ AK", "updated": "2020-11-02T16:09:51Z", "electionDate": "2020-11-03",  "categories": [{"term": "EstimatedVotePercentage", "scheme": "https:\/\/api.ap.org\/cv\/type\/"}, {"term": "true", "scheme": "https:\/\/api.ap.org\/cv\/test\/"}, {"term": "test", "scheme": "https:\/\/api.ap.org\/cv\/resultsType\/"}, {"term": "AK", "scheme": "https:\/\/api.ap.org\/cv\/geo\/"}], "contentLink": "https:\/\/api.ap.org\/v2\/reports\/6d17b969892742928e5cf5759a12e9fd"}, {"id": "https:\/\/api.ap.org\/v2\/reports\/f64575a58a79476cb7a7d3cc32ea8966", "title": "EstimatedVotePercentage \/ test \/ AL", "updated": "2020-11-02T16:09:50Z", "electionDate": "2020-11-03",  "categories": [{"term": "EstimatedVotePercentage", "scheme": "https:\/\/api.ap.org\/cv\/type\/"}, {"term": "true", "scheme": "https:\/\/api.ap.org\/cv\/test\/"}, {"term": "test", "scheme": "https:\/\/api.ap.org\/cv\/resultsType\/"}, {"term": "AL", "scheme": "https:\/\/api.ap.org\/cv\/geo\/"}], "contentLink": "https:\/\/api.ap.org\/v2\/reports\/f64575a58a79476cb7a7d3cc32ea8966"}, {"id": "https:\/\/api.ap.org\/v2\/reports\/479f8f937ec54c5d9260286cea5ebe7c", "title": "EstimatedVotePercentage \/ test \/ WV", "updated": "2020-11-02T16:08:38Z", "electionDate": "2020-11-03",  "categories": [{"term": "EstimatedVotePercentage", "scheme": "https:\/\/api.ap.org\/cv\/type\/"}, {"term": "true", "scheme": "https:\/\/api.ap.org\/cv\/test\/"}, {"term": "test", "scheme": "https:\/\/api.ap.org\/cv\/resultsType\/"}, {"term": "WV", "scheme": "https:\/\/api.ap.org\/cv\/geo\/"}], "contentLink": "https:\/\/api.ap.org\/v2\/reports\/479f8f937ec54c5d9260286cea5ebe7c"}, {"id": "https:\/\/api.ap.org\/v2\/reports\/83a028d9eae043b587b046910e5e1979", "title": "EstimatedVotePercentage \/ test \/ WY", "updated": "2020-11-02T16:08:38Z", "electionDate": "2020-11-03",  "categories": [{"term": "EstimatedVotePercentage", "scheme": "https:\/\/api.ap.org\/cv\/type\/"}, {"term": "true", "scheme": "https:\/\/api.ap.org\/cv\/test\/"}, {"term": "test", "scheme": "https:\/\/api.ap.org\/cv\/resultsType\/"}, {"term": "WY", "scheme": "https:\/\/api.ap.org\/cv\/geo\/"}], "contentLink": "https:\/\/api.ap.org\/v2\/reports\/83a028d9eae043b587b046910e5e1979"}, {"id": "https:\/\/api.ap.org\/v2\/reports\/cc186e808bfd4002ab3d29ad64a5b528", "title": "Trend \/ s \/ test \/ US", "updated": "2020-11-02T16:08:37Z", "electionDate": "2020-11-03",  "categories": [{"term": "Trend", "scheme": "https:\/\/api.ap.org\/cv\/type\/"}, {"term": "s", "scheme": "https:\/\/api.ap.org\/cv\/subtype\/"}, {"term": "true", "scheme": "https:\/\/api.ap.org\/cv\/test\/"}, {"term": "test", "scheme": "https:\/\/api.ap.org\/cv\/resultsType\/"}, {"term": "US", "scheme": "https:\/\/api.ap.org\/cv\/geo\/"}], "contentLink": "https:\/\/api.ap.org\/v2\/reports\/cc186e808bfd4002ab3d29ad64a5b528"}, {"id": "https:\/\/api.ap.org\/v2\/reports\/1add4dde5dbc45e4ab5fb1b6213bc9bd", "title": "EstimatedVotePercentage \/ test \/ WI", "updated": "2020-11-02T16:08:37Z", "electionDate": "2020-11-03",  "categories": [{"term": "EstimatedVotePercentage", "scheme": "https:\/\/api.ap.org\/cv\/type\/"}, {"term": "true", "scheme": "https:\/\/api.ap.org\/cv\/test\/"}, {"term": "test", "scheme": "https:\/\/api.ap.org\/cv\/resultsType\/"}, {"term": "WI", "scheme": "https:\/\/api.ap.org\/cv\/geo\/"}], "contentLink": "https:\/\/api.ap.org\/v2\/reports\/1add4dde5dbc45e4ab5fb1b6213bc9bd"}, {"id": "https:\/\/api.ap.org\/v2\/reports\/63435212e4384fa7938405736380cab7", "title": "Trend \/ g \/ test \/ US", "updated": "2020-11-02T16:08:37Z", "electionDate": "2020-11-03",  "categories": [{"term": "Trend", "scheme": "https:\/\/api.ap.org\/cv\/type\/"}, {"term": "g", "scheme": "https:\/\/api.ap.org\/cv\/subtype\/"}, {"term": "true", "scheme": "https:\/\/api.ap.org\/cv\/test\/"}, {"term": "test", "scheme": "https:\/\/api.ap.org\/cv\/resultsType\/"}, {"term": "US", "scheme": "https:\/\/api.ap.org\/cv\/geo\/"}], "contentLink": "https:\/\/api.ap.org\/v2\/reports\/63435212e4384fa7938405736380cab7"}, {"id": "https:\/\/api.ap.org\/v2\/reports\/2ff6f803b8514e728d9f8308ad034a73", "title": "Trend \/ h \/ test \/ US", "updated": "2020-11-02T16:08:37Z", "electionDate": "2020-11-03",  "categories": [{"term": "Trend", "scheme": "https:\/\/api.ap.org\/cv\/type\/"}, {"term": "h", "scheme": "https:\/\/api.ap.org\/cv\/subtype\/"}, {"term": "true", "scheme": "https:\/\/api.ap.org\/cv\/test\/"}, {"term": "test", "scheme": "https:\/\/api.ap.org\/cv\/resultsType\/"}, {"term": "US", "scheme": "https:\/\/api.ap.org\/cv\/geo\/"}], "contentLink": "https:\/\/api.ap.org\/v2\/reports\/2ff6f803b8514e728d9f8308ad034a73"}, {"id": "https:\/\/api.ap.org\/v2\/reports\/ed2ac781173e441299788c26bb11cf44", "title": "EstimatedVotePercentage \/ test \/ WA", "updated": "2020-11-02T16:08:36Z", "electionDate": "2020-11-03",  "categories": [{"term": "EstimatedVotePercentage", "scheme": "https:\/\/api.ap.org\/cv\/type\/"}, {"term": "true", "scheme": "https:\/\/api.ap.org\/cv\/test\/"}, {"term": "test", "scheme": "https:\/\/api.ap.org\/cv\/resultsType\/"}, {"term": "WA", "scheme": "https:\/\/api.ap.org\/cv\/geo\/"}], "contentLink": "https:\/\/api.ap.org\/v2\/reports\/ed2ac781173e441299788c26bb11cf44"}, {"id": "https:\/\/api.ap.org\/v2\/reports\/037eb5a675b1417483dc4c125c4d8d72", "title": "EstimatedVotePercentage \/ test \/ VA", "updated": "2020-11-02T16:08:34Z", "electionDate": "2020-11-03",  "categories": [{"term": "EstimatedVotePercentage", "scheme": "https:\/\/api.ap.org\/cv\/type\/"}, {"term": "true", "scheme": "https:\/\/api.ap.org\/cv\/test\/"}, {"term": "test", "scheme": "https:\/\/api.ap.org\/cv\/resultsType\/"}, {"term": "VA", "scheme": "https:\/\/api.ap.org\/cv\/geo\/"}], "contentLink": "https:\/\/api.ap.org\/v2\/reports\/037eb5a675b1417483dc4c125c4d8d72"}, {"id": "https:\/\/api.ap.org\/v2\/reports\/331c09cf9b9b4004b3261d3107241dd9", "title": "EstimatedVotePercentage \/ test \/ VT", "updated": "2020-11-02T16:08:33Z", "electionDate": "2020-11-03",  "categories": [{"term": "EstimatedVotePercentage", "scheme": "https:\/\/api.ap.org\/cv\/type\/"}, {"term": "true", "scheme": "https:\/\/api.ap.org\/cv\/test\/"}, {"term": "test", "scheme": "https:\/\/api.ap.org\/cv\/resultsType\/"}, {"term": "VT", "scheme": "https:\/\/api.ap.org\/cv\/geo\/"}], "contentLink": "https:\/\/api.ap.org\/v2\/reports\/331c09cf9b9b4004b3261d3107241dd9"}, {"id": "https:\/\/api.ap.org\/v2\/reports\/44ebb9a7aa8b44cd925e7ef4a3ef81fa", "title": "EstimatedVotePercentage \/ test \/ UT", "updated": "2020-11-02T16:08:32Z", "electionDate": "2020-11-03",  "categories": [{"term": "EstimatedVotePercentage", "scheme": "https:\/\/api.ap.org\/cv\/type\/"}, {"term": "true", "scheme": "https:\/\/api.ap.org\/cv\/test\/"}, {"term": "test", "scheme": "https:\/\/api.ap.org\/cv\/resultsType\/"}, {"term": "UT", "scheme": "https:\/\/api.ap.org\/cv\/geo\/"}], "contentLink": "https:\/\/api.ap.org\/v2\/reports\/44ebb9a7aa8b44cd925e7ef4a3ef81fa"}, {"id": "https:\/\/api.ap.org\/v2\/reports\/c8ea6293f80a4df1b42312834d0f974f", "title": "EstimatedVotePercentage \/ test \/ TX", "updated": "2020-11-02T16:08:31Z", "electionDate": "2020-11-03",  "categories": [{"term": "EstimatedVotePercentage", "scheme": "https:\/\/api.ap.org\/cv\/type\/"}, {"term": "true", "scheme": "https:\/\/api.ap.org\/cv\/test\/"}, {"term": "test", "scheme": "https:\/\/api.ap.org\/cv\/resultsType\/"}, {"term": "TX", "scheme": "https:\/\/api.ap.org\/cv\/geo\/"}], "contentLink": "https:\/\/api.ap.org\/v2\/reports\/c8ea6293f80a4df1b42312834d0f974f"}, {"id": "https:\/\/api.ap.org\/v2\/reports\/2c1729342f654fefa9f6783f3b17b814", "title": "EstimatedVotePercentage \/ test \/ SD", "updated": "2020-11-02T16:08:30Z", "electionDate": "2020-11-03",  "categories": [{"term": "EstimatedVotePercentage", "scheme": "https:\/\/api.ap.org\/cv\/type\/"}, {"term": "true", "scheme": "https:\/\/api.ap.org\/cv\/test\/"}, {"term": "test", "scheme": "https:\/\/api.ap.org\/cv\/resultsType\/"}, {"term": "SD", "scheme": "https:\/\/api.ap.org\/cv\/geo\/"}], "contentLink": "https:\/\/api.ap.org\/v2\/reports\/2c1729342f654fefa9f6783f3b17b814"}, {"id": "https:\/\/api.ap.org\/v2\/reports\/9ac6a1e97fa547cbadba146949cda7fc", "title": "EstimatedVotePercentage \/ test \/ TN", "updated": "2020-11-02T16:08:30Z", "electionDate": "2020-11-03",  "categories": [{"term": "EstimatedVotePercentage", "scheme": "https:\/\/api.ap.org\/cv\/type\/"}, {"term": "true", "scheme": "https:\/\/api.ap.org\/cv\/test\/"}, {"term": "test", "scheme": "https:\/\/api.ap.org\/cv\/resultsType\/"}, {"term": "TN", "scheme": "https:\/\/api.ap.org\/cv\/geo\/"}], "contentLink": "https:\/\/api.ap.org\/v2\/reports\/9ac6a1e97fa547cbadba146949cda7fc"}, {"id": "https:\/\/api.ap.org\/v2\/reports\/271d503728d54eb2b38136227b203c1b", "title": "EstimatedVotePercentage \/ test \/ SC", "updated": "2020-11-02T16:08:29Z", "electionDate": "2020-11-03",  "categories": [{"term": "EstimatedVotePercentage", "scheme": "https:\/\/api.ap.org\/cv\/type\/"}, {"term": "true", "scheme": "https:\/\/api.ap.org\/cv\/test\/"}, {"term": "test", "scheme": "https:\/\/api.ap.org\/cv\/resultsType\/"}, {"term": "SC", "scheme": "https:\/\/api.ap.org\/cv\/geo\/"}], "contentLink": "https:\/\/api.ap.org\/v2\/reports\/271d503728d54eb2b38136227b203c1b"}, {"id": "https:\/\/api.ap.org\/v2\/reports\/f372fa3eccaf47768b9057e1fb1287c4", "title": "EstimatedVotePercentage \/ test \/ OK", "updated": "2020-11-02T16:08:27Z", "electionDate": "2020-11-03",  "categories": [{"term": "EstimatedVotePercentage", "scheme": "https:\/\/api.ap.org\/cv\/type\/"}, {"term": "true", "scheme": "https:\/\/api.ap.org\/cv\/test\/"}, {"term": "test", "scheme": "https:\/\/api.ap.org\/cv\/resultsType\/"}, {"term": "OK", "scheme": "https:\/\/api.ap.org\/cv\/geo\/"}], "contentLink": "https:\/\/api.ap.org\/v2\/reports\/f372fa3eccaf47768b9057e1fb1287c4"}, {"id": "https:\/\/api.ap.org\/v2\/reports\/26bb5accd84646308264c919b21bb808", "title": "EstimatedVotePercentage \/ test \/ OR", "updated": "2020-11-02T16:08:27Z", "electionDate": "2020-11-03",  "categories": [{"term": "EstimatedVotePercentage", "scheme": "https:\/\/api.ap.org\/cv\/type\/"}, {"term": "true", "scheme": "https:\/\/api.ap.org\/cv\/test\/"}, {"term": "test", "scheme": "https:\/\/api.ap.org\/cv\/resultsType\/"}, {"term": "OR", "scheme": "https:\/\/api.ap.org\/cv\/geo\/"}], "contentLink": "https:\/\/api.ap.org\/v2\/reports\/26bb5accd84646308264c919b21bb808"}, {"id": "https:\/\/api.ap.org\/v2\/reports\/d991d05fcad84df498641276cea4fc30", "title": "EstimatedVotePercentage \/ test \/ PA", "updated": "2020-11-02T16:08:27Z", "electionDate": "2020-11-03",  "categories": [{"term": "EstimatedVotePercentage", "scheme": "https:\/\/api.ap.org\/cv\/type\/"}, {"term": "true", "scheme": "https:\/\/api.ap.org\/cv\/test\/"}, {"term": "test", "scheme": "https:\/\/api.ap.org\/cv\/resultsType\/"}, {"term": "PA", "scheme": "https:\/\/api.ap.org\/cv\/geo\/"}], "contentLink": "https:\/\/api.ap.org\/v2\/reports\/d991d05fcad84df498641276cea4fc30"}, {"id": "https:\/\/api.ap.org\/v2\/reports\/56c1c16115454b15b86873fa9a4eefc0", "title": "EstimatedVotePercentage \/ test \/ RI", "updated": "2020-11-02T16:08:27Z", "electionDate": "2020-11-03",  "categories": [{"term": "EstimatedVotePercentage", "scheme": "https:\/\/api.ap.org\/cv\/type\/"}, {"term": "true", "scheme": "https:\/\/api.ap.org\/cv\/test\/"}, {"term": "test", "scheme": "https:\/\/api.ap.org\/cv\/resultsType\/"}, {"term": "RI", "scheme": "https:\/\/api.ap.org\/cv\/geo\/"}], "contentLink": "https:\/\/api.ap.org\/v2\/reports\/56c1c16115454b15b86873fa9a4eefc0"}, {"id": "https:\/\/api.ap.org\/v2\/reports\/160854b6c7214f4ab93d871654831d0b", "title": "EstimatedVotePercentage \/ test \/ NC", "updated": "2020-11-02T16:08:23Z", "electionDate": "2020-11-03",  "categories": [{"term": "EstimatedVotePercentage", "scheme": "https:\/\/api.ap.org\/cv\/type\/"}, {"term": "true", "scheme": "https:\/\/api.ap.org\/cv\/test\/"}, {"term": "test", "scheme": "https:\/\/api.ap.org\/cv\/resultsType\/"}, {"term": "NC", "scheme": "https:\/\/api.ap.org\/cv\/geo\/"}], "contentLink": "https:\/\/api.ap.org\/v2\/reports\/160854b6c7214f4ab93d871654831d0b"}, {"id": "https:\/\/api.ap.org\/v2\/reports\/d2c2dad2431d4cc0ab59182101d4b131", "title": "EstimatedVotePercentage \/ test \/ ND", "updated": "2020-11-02T16:08:23Z", "electionDate": "2020-11-03",  "categories": [{"term": "EstimatedVotePercentage", "scheme": "https:\/\/api.ap.org\/cv\/type\/"}, {"term": "true", "scheme": "https:\/\/api.ap.org\/cv\/test\/"}, {"term": "test", "scheme": "https:\/\/api.ap.org\/cv\/resultsType\/"}, {"term": "ND", "scheme": "https:\/\/api.ap.org\/cv\/geo\/"}], "contentLink": "https:\/\/api.ap.org\/v2\/reports\/d2c2dad2431d4cc0ab59182101d4b131"}, {"id": "https:\/\/api.ap.org\/v2\/reports\/3cb9141a0f5645088cd68b21894e6b47", "title": "EstimatedVotePercentage \/ test \/ NY", "updated": "2020-11-02T16:08:23Z", "electionDate": "2020-11-03",  "categories": [{"term": "EstimatedVotePercentage", "scheme": "https:\/\/api.ap.org\/cv\/type\/"}, {"term": "true", "scheme": "https:\/\/api.ap.org\/cv\/test\/"}, {"term": "test", "scheme": "https:\/\/api.ap.org\/cv\/resultsType\/"}, {"term": "NY", "scheme": "https:\/\/api.ap.org\/cv\/geo\/"}], "contentLink": "https:\/\/api.ap.org\/v2\/reports\/3cb9141a0f5645088cd68b21894e6b47"}, {"id": "https:\/\/api.ap.org\/v2\/reports\/18cb8d1f1564477ea3ad8a3d8e7967f9", "title": "EstimatedVotePercentage \/ test \/ OH", "updated": "2020-11-02T16:08:23Z", "electionDate": "2020-11-03",  "categories": [{"term": "EstimatedVotePercentage", "scheme": "https:\/\/api.ap.org\/cv\/type\/"}, {"term": "true", "scheme": "https:\/\/api.ap.org\/cv\/test\/"}, {"term": "test", "scheme": "https:\/\/api.ap.org\/cv\/resultsType\/"}, {"term": "OH", "scheme": "https:\/\/api.ap.org\/cv\/geo\/"}], "contentLink": "https:\/\/api.ap.org\/v2\/reports\/18cb8d1f1564477ea3ad8a3d8e7967f9"}, {"id": "https:\/\/api.ap.org\/v2\/reports\/0cec116d8a6a4715b9648e3d49993998", "title": "EstimatedVotePercentage \/ test \/ NH", "updated": "2020-11-02T16:08:23Z", "electionDate": "2020-11-03",  "categories": [{"term": "EstimatedVotePercentage", "scheme": "https:\/\/api.ap.org\/cv\/type\/"}, {"term": "true", "scheme": "https:\/\/api.ap.org\/cv\/test\/"}, {"term": "test", "scheme": "https:\/\/api.ap.org\/cv\/resultsType\/"}, {"term": "NH", "scheme": "https:\/\/api.ap.org\/cv\/geo\/"}], "contentLink": "https:\/\/api.ap.org\/v2\/reports\/0cec116d8a6a4715b9648e3d49993998"}, {"id": "https:\/\/api.ap.org\/v2\/reports\/6d136a6f2cf54c2eaa19a0fd77b50d19", "title": "EstimatedVotePercentage \/ test \/ NJ", "updated": "2020-11-02T16:08:23Z", "electionDate": "2020-11-03",  "categories": [{"term": "EstimatedVotePercentage", "scheme": "https:\/\/api.ap.org\/cv\/type\/"}, {"term": "true", "scheme": "https:\/\/api.ap.org\/cv\/test\/"}, {"term": "test", "scheme": "https:\/\/api.ap.org\/cv\/resultsType\/"}, {"term": "NJ", "scheme": "https:\/\/api.ap.org\/cv\/geo\/"}], "contentLink": "https:\/\/api.ap.org\/v2\/reports\/6d136a6f2cf54c2eaa19a0fd77b50d19"}, {"id": "https:\/\/api.ap.org\/v2\/reports\/c9a3b3dec05b48389f3b398bab8c0f91", "title": "EstimatedVotePercentage \/ test \/ NM", "updated": "2020-11-02T16:08:22Z", "electionDate": "2020-11-03",  "categories": [{"term": "EstimatedVotePercentage", "scheme": "https:\/\/api.ap.org\/cv\/type\/"}, {"term": "true", "scheme": "https:\/\/api.ap.org\/cv\/test\/"}, {"term": "test", "scheme": "https:\/\/api.ap.org\/cv\/resultsType\/"}, {"term": "NM", "scheme": "https:\/\/api.ap.org\/cv\/geo\/"}], "contentLink": "https:\/\/api.ap.org\/v2\/reports\/c9a3b3dec05b48389f3b398bab8c0f91"}, {"id": "https:\/\/api.ap.org\/v2\/reports\/93db8fac2bcc484ca66ce3c5b4927fda", "title": "EstimatedVotePercentage \/ test \/ NV", "updated": "2020-11-02T16:08:16Z", "electionDate": "2020-11-03",  "categories": [{"term": "EstimatedVotePercentage", "scheme": "https:\/\/api.ap.org\/cv\/type\/"}, {"term": "true", "scheme": "https:\/\/api.ap.org\/cv\/test\/"}, {"term": "test", "scheme": "https:\/\/api.ap.org\/cv\/resultsType\/"}, {"term": "NV", "scheme": "https:\/\/api.ap.org\/cv\/geo\/"}], "contentLink": "https:\/\/api.ap.org\/v2\/reports\/93db8fac2bcc484ca66ce3c5b4927fda"}, {"id": "https:\/\/api.ap.org\/v2\/reports\/b090f1dca5664166a8ce7c16f0324a69", "title": "EstimatedVotePercentage \/ test \/ MT", "updated": "2020-11-02T16:08:15Z", "electionDate": "2020-11-03",  "categories": [{"term": "EstimatedVotePercentage", "scheme": "https:\/\/api.ap.org\/cv\/type\/"}, {"term": "true", "scheme": "https:\/\/api.ap.org\/cv\/test\/"}, {"term": "test", "scheme": "https:\/\/api.ap.org\/cv\/resultsType\/"}, {"term": "MT", "scheme": "https:\/\/api.ap.org\/cv\/geo\/"}], "contentLink": "https:\/\/api.ap.org\/v2\/reports\/b090f1dca5664166a8ce7c16f0324a69"}, {"id": "https:\/\/api.ap.org\/v2\/reports\/a70f9419e43e46b9a6c09bdbe64c6ebf", "title": "EstimatedVotePercentage \/ test \/ MO", "updated": "2020-11-02T16:08:13Z", "electionDate": "2020-11-03",  "categories": [{"term": "EstimatedVotePercentage", "scheme": "https:\/\/api.ap.org\/cv\/type\/"}, {"term": "true", "scheme": "https:\/\/api.ap.org\/cv\/test\/"}, {"term": "test", "scheme": "https:\/\/api.ap.org\/cv\/resultsType\/"}, {"term": "MO", "scheme": "https:\/\/api.ap.org\/cv\/geo\/"}], "contentLink": "https:\/\/api.ap.org\/v2\/reports\/a70f9419e43e46b9a6c09bdbe64c6ebf"}, {"id": "https:\/\/api.ap.org\/v2\/reports\/fe1191c48cb5438aa8a437319ccafe37", "title": "EstimatedVotePercentage \/ test \/ MS", "updated": "2020-11-02T16:08:13Z", "electionDate": "2020-11-03",  "categories": [{"term": "EstimatedVotePercentage", "scheme": "https:\/\/api.ap.org\/cv\/type\/"}, {"term": "true", "scheme": "https:\/\/api.ap.org\/cv\/test\/"}, {"term": "test", "scheme": "https:\/\/api.ap.org\/cv\/resultsType\/"}, {"term": "MS", "scheme": "https:\/\/api.ap.org\/cv\/geo\/"}], "contentLink": "https:\/\/api.ap.org\/v2\/reports\/fe1191c48cb5438aa8a437319ccafe37"}, {"id": "https:\/\/api.ap.org\/v2\/reports\/1b2eca20e59f429dbe6a9ceb882cbcad", "title": "EstimatedVotePercentage \/ test \/ MI", "updated": "2020-11-02T16:08:13Z", "electionDate": "2020-11-03",  "categories": [{"term": "EstimatedVotePercentage", "scheme": "https:\/\/api.ap.org\/cv\/type\/"}, {"term": "true", "scheme": "https:\/\/api.ap.org\/cv\/test\/"}, {"term": "test", "scheme": "https:\/\/api.ap.org\/cv\/resultsType\/"}, {"term": "MI", "scheme": "https:\/\/api.ap.org\/cv\/geo\/"}], "contentLink": "https:\/\/api.ap.org\/v2\/reports\/1b2eca20e59f429dbe6a9ceb882cbcad"}, {"id": "https:\/\/api.ap.org\/v2\/reports\/becc4b66bc1d4891a4513e4b64f71b93", "title": "EstimatedVotePercentage \/ test \/ NE", "updated": "2020-11-02T16:08:13Z", "electionDate": "2020-11-03",  "categories": [{"term": "EstimatedVotePercentage", "scheme": "https:\/\/api.ap.org\/cv\/type\/"}, {"term": "true", "scheme": "https:\/\/api.ap.org\/cv\/test\/"}, {"term": "test", "scheme": "https:\/\/api.ap.org\/cv\/resultsType\/"}, {"term": "NE", "scheme": "https:\/\/api.ap.org\/cv\/geo\/"}], "contentLink": "https:\/\/api.ap.org\/v2\/reports\/becc4b66bc1d4891a4513e4b64f71b93"}, {"id": "https:\/\/api.ap.org\/v2\/reports\/709059d3ab244395b44e4ad21cfeff73", "title": "EstimatedVotePercentage \/ test \/ MN", "updated": "2020-11-02T16:08:11Z", "electionDate": "2020-11-03",  "categories": [{"term": "EstimatedVotePercentage", "scheme": "https:\/\/api.ap.org\/cv\/type\/"}, {"term": "true", "scheme": "https:\/\/api.ap.org\/cv\/test\/"}, {"term": "test", "scheme": "https:\/\/api.ap.org\/cv\/resultsType\/"}, {"term": "MN", "scheme": "https:\/\/api.ap.org\/cv\/geo\/"}], "contentLink": "https:\/\/api.ap.org\/v2\/reports\/709059d3ab244395b44e4ad21cfeff73"}, {"id": "https:\/\/api.ap.org\/v2\/reports\/fc9ff80e9317456abfeddd6aa23fe27d", "title": "EstimatedVotePercentage \/ test \/ MD", "updated": "2020-11-02T16:08:11Z", "electionDate": "2020-11-03",  "categories": [{"term": "EstimatedVotePercentage", "scheme": "https:\/\/api.ap.org\/cv\/type\/"}, {"term": "true", "scheme": "https:\/\/api.ap.org\/cv\/test\/"}, {"term": "test", "scheme": "https:\/\/api.ap.org\/cv\/resultsType\/"}, {"term": "MD", "scheme": "https:\/\/api.ap.org\/cv\/geo\/"}], "contentLink": "https:\/\/api.ap.org\/v2\/reports\/fc9ff80e9317456abfeddd6aa23fe27d"}, {"id": "https:\/\/api.ap.org\/v2\/reports\/f1bb92a6a14143139f841710e53d9f1e", "title": "EstimatedVotePercentage \/ test \/ ME", "updated": "2020-11-02T16:08:10Z", "electionDate": "2020-11-03",  "categories": [{"term": "EstimatedVotePercentage", "scheme": "https:\/\/api.ap.org\/cv\/type\/"}, {"term": "true", "scheme": "https:\/\/api.ap.org\/cv\/test\/"}, {"term": "test", "scheme": "https:\/\/api.ap.org\/cv\/resultsType\/"}, {"term": "ME", "scheme": "https:\/\/api.ap.org\/cv\/geo\/"}], "contentLink": "https:\/\/api.ap.org\/v2\/reports\/f1bb92a6a14143139f841710e53d9f1e"}, {"id": "https:\/\/api.ap.org\/v2\/reports\/5ad77df6c2c943d0827debb7f8cbdc6a", "title": "EstimatedVotePercentage \/ test \/ MA", "updated": "2020-11-02T16:08:09Z", "electionDate": "2020-11-03",  "categories": [{"term": "EstimatedVotePercentage", "scheme": "https:\/\/api.ap.org\/cv\/type\/"}, {"term": "true", "scheme": "https:\/\/api.ap.org\/cv\/test\/"}, {"term": "test", "scheme": "https:\/\/api.ap.org\/cv\/resultsType\/"}, {"term": "MA", "scheme": "https:\/\/api.ap.org\/cv\/geo\/"}], "contentLink": "https:\/\/api.ap.org\/v2\/reports\/5ad77df6c2c943d0827debb7f8cbdc6a"}, {"id": "https:\/\/api.ap.org\/v2\/reports\/c0133b912fce4ef990198bc561e3b6eb", "title": "EstimatedVotePercentage \/ test \/ LA", "updated": "2020-11-02T16:08:07Z", "electionDate": "2020-11-03",  "categories": [{"term": "EstimatedVotePercentage", "scheme": "https:\/\/api.ap.org\/cv\/type\/"}, {"term": "true", "scheme": "https:\/\/api.ap.org\/cv\/test\/"}, {"term": "test", "scheme": "https:\/\/api.ap.org\/cv\/resultsType\/"}, {"term": "LA", "scheme": "https:\/\/api.ap.org\/cv\/geo\/"}], "contentLink": "https:\/\/api.ap.org\/v2\/reports\/c0133b912fce4ef990198bc561e3b6eb"}, {"id": "https:\/\/api.ap.org\/v2\/reports\/524c86009fa3418ba4086d9450a62269", "title": "EstimatedVotePercentage \/ test \/ KY", "updated": "2020-11-02T16:08:06Z", "electionDate": "2020-11-03",  "categories": [{"term": "EstimatedVotePercentage", "scheme": "https:\/\/api.ap.org\/cv\/type\/"}, {"term": "true", "scheme": "https:\/\/api.ap.org\/cv\/test\/"}, {"term": "test", "scheme": "https:\/\/api.ap.org\/cv\/resultsType\/"}, {"term": "KY", "scheme": "https:\/\/api.ap.org\/cv\/geo\/"}], "contentLink": "https:\/\/api.ap.org\/v2\/reports\/524c86009fa3418ba4086d9450a62269"}, {"id": "https:\/\/api.ap.org\/v2\/reports\/6b4a3a77aa234998bb64e417a9353745", "title": "EstimatedVotePercentage \/ test \/ IN", "updated": "2020-11-02T16:08:06Z", "electionDate": "2020-11-03",  "categories": [{"term": "EstimatedVotePercentage", "scheme": "https:\/\/api.ap.org\/cv\/type\/"}, {"term": "true", "scheme": "https:\/\/api.ap.org\/cv\/test\/"}, {"term": "test", "scheme": "https:\/\/api.ap.org\/cv\/resultsType\/"}, {"term": "IN", "scheme": "https:\/\/api.ap.org\/cv\/geo\/"}], "contentLink": "https:\/\/api.ap.org\/v2\/reports\/6b4a3a77aa234998bb64e417a9353745"}, {"id": "https:\/\/api.ap.org\/v2\/reports\/e13df7e934e249eb81d238cb9dbf0714", "title": "EstimatedVotePercentage \/ test \/ KS", "updated": "2020-11-02T16:08:04Z", "electionDate": "2020-11-03",  "categories": [{"term": "EstimatedVotePercentage", "scheme": "https:\/\/api.ap.org\/cv\/type\/"}, {"term": "true", "scheme": "https:\/\/api.ap.org\/cv\/test\/"}, {"term": "test", "scheme": "https:\/\/api.ap.org\/cv\/resultsType\/"}, {"term": "KS", "scheme": "https:\/\/api.ap.org\/cv\/geo\/"}], "contentLink": "https:\/\/api.ap.org\/v2\/reports\/e13df7e934e249eb81d238cb9dbf0714"}, {"id": "https:\/\/api.ap.org\/v2\/reports\/66c0510ef37f42999947f04c7be3725e", "title": "EstimatedVotePercentage \/ test \/ IA", "updated": "2020-11-02T16:08:02Z", "electionDate": "2020-11-03",  "categories": [{"term": "EstimatedVotePercentage", "scheme": "https:\/\/api.ap.org\/cv\/type\/"}, {"term": "true", "scheme": "https:\/\/api.ap.org\/cv\/test\/"}, {"term": "test", "scheme": "https:\/\/api.ap.org\/cv\/resultsType\/"}, {"term": "IA", "scheme": "https:\/\/api.ap.org\/cv\/geo\/"}], "contentLink": "https:\/\/api.ap.org\/v2\/reports\/66c0510ef37f42999947f04c7be3725e"}, {"id": "https:\/\/api.ap.org\/v2\/reports\/258ec90705d648d8bff824383f7c366d", "title": "EstimatedVotePercentage \/ test \/ GA", "updated": "2020-11-02T16:08:01Z", "electionDate": "2020-11-03",  "categories": [{"term": "EstimatedVotePercentage", "scheme": "https:\/\/api.ap.org\/cv\/type\/"}, {"term": "true", "scheme": "https:\/\/api.ap.org\/cv\/test\/"}, {"term": "test", "scheme": "https:\/\/api.ap.org\/cv\/resultsType\/"}, {"term": "GA", "scheme": "https:\/\/api.ap.org\/cv\/geo\/"}], "contentLink": "https:\/\/api.ap.org\/v2\/reports\/258ec90705d648d8bff824383f7c366d"}, {"id": "https:\/\/api.ap.org\/v2\/reports\/65943bc313114394a9b6e3ba616c7010", "title": "trend \/ hs \/ test \/ US", "updated": "2020-10-30T20:44:46Z", "electionDate": "2020-11-03",  "categories": [{"term": "trend", "scheme": "https:\/\/api.ap.org\/cv\/type\/"}, {"term": "hs", "scheme": "https:\/\/api.ap.org\/cv\/subtype\/"}, {"term": "true", "scheme": "https:\/\/api.ap.org\/cv\/test\/"}, {"term": "test", "scheme": "https:\/\/api.ap.org\/cv\/resultsType\/"}, {"term": "US", "scheme": "https:\/\/api.ap.org\/cv\/geo\/"}], "contentLink": "https:\/\/api.ap.org\/v2\/reports\/65943bc313114394a9b6e3ba616c7010"}, {"id": "https:\/\/api.ap.org\/v2\/reports\/2164bab92e1e425d8ed62db5ed861377", "title": "trend \/ sa \/ test \/ US", "updated": "2020-10-30T20:44:42Z", "electionDate": "2020-11-03",  "categories": [{"term": "trend", "scheme": "https:\/\/api.ap.org\/cv\/type\/"}, {"term": "sa", "scheme": "https:\/\/api.ap.org\/cv\/subtype\/"}, {"term": "true", "scheme": "https:\/\/api.ap.org\/cv\/test\/"}, {"term": "test", "scheme": "https:\/\/api.ap.org\/cv\/resultsType\/"}, {"term": "US", "scheme": "https:\/\/api.ap.org\/cv\/geo\/"}], "contentLink": "https:\/\/api.ap.org\/v2\/reports\/2164bab92e1e425d8ed62db5ed861377"}, {"id": "https:\/\/api.ap.org\/v2\/reports\/a6485375a3a34f41b929b795decce55c", "title": "AdvVotes \/ advturnout2020GE \/ test", "updated": "2020-10-23T11:29:08Z",  "categories": [{"term": "AdvVotes", "scheme": "https:\/\/api.ap.org\/cv\/type\/"}, {"term": "advturnout2020GE", "scheme": "https:\/\/api.ap.org\/cv\/subtype\/"}, {"term": "true", "scheme": "https:\/\/api.ap.org\/cv\/test\/"}, {"term": "test", "scheme": "https:\/\/api.ap.org\/cv\/resultsType\/"}], "contentLink": "https:\/\/api.ap.org\/v2\/reports\/a6485375a3a34f41b929b795decce55c"}, {"id": "https:\/\/api.ap.org\/v2\/reports\/26556084870a4019ab10786489e13843", "title": "AdvVotes \/ advvotingrules2020GE \/ test", "updated": "2020-10-15T23:05:01Z",  "categories": [{"term": "AdvVotes", "scheme": "https:\/\/api.ap.org\/cv\/type\/"}, {"term": "advvotingrules2020GE", "scheme": "https:\/\/api.ap.org\/cv\/subtype\/"}, {"term": "true", "scheme": "https:\/\/api.ap.org\/cv\/test\/"}, {"term": "test", "scheme": "https:\/\/api.ap.org\/cv\/resultsType\/"}], "contentLink": "https:\/\/api.ap.org\/v2\/reports\/26556084870a4019ab10786489e13843"}, {"id": "https:\/\/api.ap.org\/v2\/reports\/db5d9251ed164ad3858ed4c74065fcb9", "title": "WI \/ EstimatedVotePercentage \/ test", "updated": "2020-10-07T15:51:49Z",  "categories": [{"term": "WI", "scheme": "https:\/\/api.ap.org\/cv\/type\/"}, {"term": "EstimatedVotePercentage", "scheme": "https:\/\/api.ap.org\/cv\/subtype\/"}, {"term": "true", "scheme": "https:\/\/api.ap.org\/cv\/test\/"}, {"term": "test", "scheme": "https:\/\/api.ap.org\/cv\/resultsType\/"}], "contentLink": "https:\/\/api.ap.org\/v2\/reports\/db5d9251ed164ad3858ed4c74065fcb9"}, {"id": "https:\/\/api.ap.org\/v2\/reports\/c64b2e99b676438c8ba882c0e1aab3a7", "title": "TX \/ EstimatedVotePercentage \/ test", "updated": "2020-10-07T15:43:42Z",  "categories": [{"term": "TX", "scheme": "https:\/\/api.ap.org\/cv\/type\/"}, {"term": "EstimatedVotePercentage", "scheme": "https:\/\/api.ap.org\/cv\/subtype\/"}, {"term": "true", "scheme": "https:\/\/api.ap.org\/cv\/test\/"}, {"term": "test", "scheme": "https:\/\/api.ap.org\/cv\/resultsType\/"}], "contentLink": "https:\/\/api.ap.org\/v2\/reports\/c64b2e99b676438c8ba882c0e1aab3a7"}, {"id": "https:\/\/api.ap.org\/v2\/reports\/99ff9387158442a9b67621ac70a1624f", "title": "Candidates \/ Governor2020 \/ test", "updated": "2020-07-23T14:46:35Z",  "categories": [{"term": "Candidates", "scheme": "https:\/\/api.ap.org\/cv\/type\/"}, {"term": "Governor2020", "scheme": "https:\/\/api.ap.org\/cv\/subtype\/"}, {"term": "true", "scheme": "https:\/\/api.ap.org\/cv\/test\/"}, {"term": "test", "scheme": "https:\/\/api.ap.org\/cv\/resultsType\/"}], "contentLink": "https:\/\/api.ap.org\/v2\/reports\/99ff9387158442a9b67621ac70a1624f"}], "nextrequest": "https:\/\/api.ap.org\/v2\/reports?test=true&format=json&minDateTime=2020-11-02T16%3a10%3a01.000Z"}